polyroi/Point.py
polyroi/Shape.py
polyroi/__init__.py
polyroi-0.0.4.dist-info/LICENSE
polyroi-0.0.4.dist-info/METADATA
polyroi-0.0.4.dist-info/WHEEL
polyroi-0.0.4.dist-info/top_level.txt
polyroi-0.0.4.dist-info/RECORD
