Metadata-Version: 2.1
Name: polyroi
Version: 0.0.4
Summary: This tool help in extracting the region of interest in a given image.
Home-page: https://github.com/skywolfmo/polyroi
Author: Taha Bouhsine
Author-email: skywolf.mo@gmail.com
License: UNKNOWN
Project-URL: Bug Tracker, https://github.com/skywolfmo/polyroi/issues
Platform: UNKNOWN
Classifier: Programming Language :: Python :: 3
Classifier: License :: OSI Approved :: MIT License
Classifier: Operating System :: OS Independent
Requires-Python: >=3.6
License-File: LICENSE
Requires-Dist: numpy
Requires-Dist: opencv-python
